aio_conf/Developer_Toolkit/__init__.py
aio_conf/Developer_Toolkit/builder.py
aio_conf/Developer_Toolkit/dumper.py
aio_conf/Developer_Toolkit/validator.py
aio_conf/__init__.py
aio_conf/core/__init__.py
aio_conf/core/aio_config.py
aio_conf/core/conf_spec.py
aio_conf/core/opt_spec.py
aio_conf/loader/__init__.py
aio_conf/loader/cli/__init__.py
aio_conf/loader/cli/protocols.py
aio_conf/writer.py
aio_conf-1.0.0.dev7.dist-info/METADATA
aio_conf-1.0.0.dev7.dist-info/WHEEL
aio_conf-1.0.0.dev7.dist-info/RECORD
