Metadata-Version: 2.3
Name: aio-conf
Version: 1.0.0.dev7
Summary: 
Author: t.blackstone
Author-email: t.blackstone@inspyre.tech
Requires-Python: >=3.12
Classifier: Programming Language :: Python :: 3
Classifier: Programming Language :: Python :: 3.12
Classifier: Programming Language :: Python :: 3.13
Requires-Dist: notebook (>=7.4.5,<8.0.0)
Requires-Dist: pysimplegui-4-foss (==4.60.4.1)
Requires-Dist: pyyaml (>=6.0)
Requires-Dist: streamlit (>=1.47.1,<2.0.0)
